{
  "search_text": "Search weather by city or ZIP",

  "feels_like": "Feels like",
  "wind": "Wind",
  "wind_units": "m/s",
  "humidity": "Humidity",

  "latitude": "Latitude",
  "longitude": "Longitude",

  "week_day_monday_short": "Mon",
  "week_day_tuesday_short": "Tue",
  "week_day_wednesday_short": "Wed",
  "week_day_thursday_short": "Thu",
  "week_day_friday_short": "Fri",
  "week_day_saturday_short": "Sat",
  "week_day_sunday_short": "Sun",

  "week_day_monday": "Monday",
  "week_day_tuesday": "Tuesday",
  "week_day_wednesday": "Wednesday",
  "week_day_thursday": "Thursday",
  "week_day_friday": "Friday",
  "week_day_saturday": "Saturday",
  "week_day_sunday": "Sunday",

  "month_january": "January",
  "month_february": "February",
  "month_march": "March",
  "month_april": "April",
  "month_may": "May",
  "month_june": "June",
  "month_july": "July",
  "month_august": "August",
  "month_september": "September",
  "month_october": "October",
  "month_november": "November",
  "month_december": "December",

  "weather_description_200": "Thunderstorm with light rain",
  "weather_description_201": "Thunderstorm with rain",
  "weather_description_202": "Thunderstorm with heavy rain",
  "weather_description_231": "Thunderstorm with drizzle",
  "weather_description_232": "Thunderstorm with heavy drizzle",
  "weather_description_233": "Thunderstorm with Hail",
  "weather_description_300": "Light Drizzle",
  "weather_description_301": "Drizzle",
  "weather_description_302": "Heavy Drizzle",
  "weather_description_500": "Light Rain",
  "weather_description_501": "Moderate Rain",
  "weather_description_502": "Heavy Rain",
  "weather_description_511": "Freezing rain",
  "weather_description_520": "Light shower rain",
  "weather_description_521": "Shower rain",
  "weather_description_522": "Heavy shower rain",
  "weather_description_600": "Light snow",
  "weather_description_601": "Snow",
  "weather_description_602": "Heavy Snow",
  "weather_description_610": "Mix snow/rain",
  "weather_description_611": "Sleet",
  "weather_description_612": "Heavy sleet",
  "weather_description_621": "Snow shower",
  "weather_description_622": "Heavy snow shower",
  "weather_description_623": "Flurries",
  "weather_description_700": "Mist",
  "weather_description_711": "Smoke",
  "weather_description_721": "Haze",
  "weather_description_731": "Sand/dust",
  "weather_description_741": "Fog",
  "weather_description_751": "Freezing Fog",
  "weather_description_800": "Clear sky",
  "weather_description_801": "Few clouds",
  "weather_description_802": "Scattered clouds",
  "weather_description_803": "Broken clouds",
  "weather_description_804": "Overcast clouds",
  "weather_description_900": "Unknown Precipitation",

  "error_no_connection": "No internet connection!",
  "error_empty_query": "Empty string entered!",
  "error_not_found": "Query not found!",
  "error_unsplash_images_exceeded_limit": "Exceeded image limit for this hour!"
}
